hgicommon/__init__.py
hgicommon/collections.py
hgicommon/enums.py
hgicommon/helpers.py
hgicommon/managers.py
hgicommon/models.py
hgicommon/testing.py
hgicommon/data_source/__init__.py
hgicommon/data_source/basic.py
hgicommon/data_source/common.py
hgicommon/data_source/dynamic_from_file.py
hgicommon/data_source/static_from_file.py
hgicommon/decorators/__init__.py
hgicommon/decorators/gotta_catchem_all.py
hgicommon/docker/__init__.py
hgicommon/docker/client.py
hgicommon/docker/models.py
hgicommon/mixable/__init__.py
hgicommon/mixable/listenable.py
hgicommon/mixable/priority.py
hgicommon/tests/__init__.py
hgicommon/tests/_helpers.py
hgicommon/tests/_stubs.py
hgicommon/tests/test_collection.py
hgicommon/tests/test_helpers.py
hgicommon/tests/test_managers.py
hgicommon/tests/test_models.py
hgicommon/tests/test_testing.py
hgicommon/tests/data_source/__init__.py
hgicommon/tests/data_source/_helpers.py
hgicommon/tests/data_source/_stubs.py
hgicommon/tests/data_source/test_basic.py
hgicommon/tests/data_source/test_dynamic_from_file.py
hgicommon/tests/data_source/test_static_from_file.py
hgicommon/tests/decorators/__init__.py
hgicommon/tests/decorators/test_gotta_catchem_all.py
hgicommon/tests/mixable/__init__.py
hgicommon/tests/mixable/test_listenable.py
hgicommon/tests/mixable/test_priority.py
hgicommon/tests/threading/__init__.py
hgicommon/tests/threading/test_counting_lock.py
hgicommon/threading/__init__.py
hgicommon/threading/counting_lock.py
hgicommon-1.3.2.dist-info/licenses/LICENSE.txt
hgicommon-1.3.2.dist-info/METADATA
hgicommon-1.3.2.dist-info/WHEEL
hgicommon-1.3.2.dist-info/top_level.txt
hgicommon-1.3.2.dist-info/RECORD
