Metadata-Version: 2.4
Name: hgicommon
Version: 1.3.2
Summary: Common Python code used in HGI projects.
Home-page: https://github.com/wtsi-hgi/python-common
Author: Colin Nolan
Author-email: colin.nolan@sanger.ac.uk
License: LGPL
Classifier: Intended Audience :: Developers
Classifier: Operating System :: OS Independent
Classifier: Programming Language :: Python :: 3.5
Classifier: License :: OSI Approved :: GNU Lesser General Public License v3 (LGPLv3)
License-File: LICENSE.txt
Requires-Dist: watchdog>=0.8.3
Requires-Dist: docker>=2.0.1
Dynamic: author
Dynamic: author-email
Dynamic: classifier
Dynamic: description
Dynamic: home-page
Dynamic: license
Dynamic: license-file
Dynamic: requires-dist
Dynamic: summary
